Metadata-Version: 2.1
Name: zpy-database
Version: 0.1.1
Summary: Pyton database wrapper
Home-page: https://github.com/zguillez/zpy-database
Author: Guillermo de la Iglesia
Author-email: mail@zguillez.io
Classifier: Programming Language :: Python :: 3
Classifier: License :: OSI Approved :: MIT License
Classifier: Operating System :: OS Independent
License-File: LICENSE
